setup.py
minirony/__init__.py
minirony/data_transfer.py
minirony/factory.py
minirony/helper.py
minirony/manager.py
minirony/provider.py
minirony.egg-info/PKG-INFO
minirony.egg-info/SOURCES.txt
minirony.egg-info/dependency_links.txt
minirony.egg-info/top_level.txt