Metadata-Version: 2.1
Name: minirony
Version: 0.0.3
Summary: Pacote com os jars
Author: Skywalker's
